nonebot_plugin_soup/__init__.py
nonebot_plugin_soup/config.py
nonebot_plugin_soup-1.1.0.dist-info/LICENSE
nonebot_plugin_soup-1.1.0.dist-info/METADATA
nonebot_plugin_soup-1.1.0.dist-info/WHEEL
nonebot_plugin_soup-1.1.0.dist-info/RECORD
