Metadata-Version: 2.1
Name: nonebot-plugin-soup
Version: 1.1.0
Summary: 来一碗心灵鸡汤吧♥
Home-page: https://github.com/Monarchdos/nonebot_plugin_soup
Keywords: nonebot,nonebot2,ChickenSoup
Author: Monarchdos
Author-email: admin@ayfre.com
Requires-Python: >=3.8,<4.0
Classifier: Programming Language :: Python :: 3
Classifier: Programming Language :: Python :: 3.8
Classifier: Programming Language :: Python :: 3.9
Classifier: Programming Language :: Python :: 3.10
Classifier: Programming Language :: Python :: 3.11
Classifier: Programming Language :: Python :: 3.12
Requires-Dist: nonebot-adapter-onebot (>=2.0.0-beta.1,<3.0.0)
Requires-Dist: nonebot2 (>=2.0.0-beta.1,<3.0.0)
Requires-Dist: requests
Project-URL: Documentation, https://github.com/Monarchdos/nonebot_plugin_soup#readme
Project-URL: Repository, https://github.com/Monarchdos/nonebot_plugin_soup
